_jump.cpython-312-aarch64-linux-musl.so
jump/__init__.py
jump/__init__.pyi
jump/jump.c
jump/py.typed
jump_consistent_hash-3.5.2.dist-info/METADATA
jump_consistent_hash-3.5.2.dist-info/WHEEL
jump_consistent_hash-3.5.2.dist-info/top_level.txt
jump_consistent_hash-3.5.2.dist-info/RECORD
jump_consistent_hash-3.5.2.dist-info/licenses/LICENSE
