Metadata-Version: 2.4
Name: jump-consistent-hash
Version: 3.5.2
Summary: Implementation of the Jump Consistent Hash algorithm
Author-email: Peter Lithammer <peter.lithammer@gmail.com>
License-Expression: MIT
Project-URL: Source, https://github.com/lithammer/python-jump-consistent-hash
Project-URL: Issues, https://github.com/lithammer/python-jump-consistent-hash/issues
Project-URL: Changelog, https://github.com/lithammer/python-jump-consistent-hash/releases
Project-URL: Documentation, https://github.com/lithammer/python-jump-consistent-hash#readme
Keywords: jump,consistent,hash,jumphash,algorithm
Classifier: Development Status :: 5 - Production/Stable
Classifier: Intended Audience :: Developers
Classifier: Operating System :: MacOS :: MacOS X
Classifier: Operating System :: Microsoft :: Windows
Classifier: Operating System :: POSIX
Classifier: Programming Language :: Python :: 3
Classifier: Programming Language :: Python :: 3.9
Classifier: Programming Language :: Python :: 3.10
Classifier: Programming Language :: Python :: 3.11
Classifier: Programming Language :: Python :: 3.12
Classifier: Programming Language :: Python :: 3.13
Classifier: Programming Language :: Python :: 3.14
Requires-Python: >=3.9
License-File: LICENSE
Dynamic: license-file
